server/__init__.py
server/convert.py
server/rpc_server.py
server/test.py
server/examples/__init__.py
server/examples/python/__init__.py
server/examples/python/converter_pb2.py
server/examples/python/converter_pb2_grpc.py
server/examples/python/rpc_client.py
server/exception/BaseException.py
server/exception/ConvertException.py
server/exception/__init__.py
server/rpc/__init__.py
server/rpc/converter_pb2.py
server/rpc/converter_pb2_grpc.py
server/service/Convert.py
server/service/File.py
server/service/GltfPipeline.py
server/service/__init__.py
server/service/stl2gltf.py
server/service/upload.py
anhdhanhdh-1.1.2.dist-info/LICENSE
anhdhanhdh-1.1.2.dist-info/METADATA
anhdhanhdh-1.1.2.dist-info/WHEEL
anhdhanhdh-1.1.2.dist-info/top_level.txt
anhdhanhdh-1.1.2.dist-info/RECORD
