Metadata-Version: 2.1
Name: anhdhanhdh
Version: 1.1.2
Summary: My first Python package
Author: anhdhanhdh
Author-email: <anhdhanhdh@email.com>
Keywords: python,first package
Classifier: Development Status :: 3 - Alpha
Classifier: Intended Audience :: Education
Classifier: Programming Language :: Python :: 2
Classifier: Programming Language :: Python :: 3
Classifier: Operating System :: MacOS :: MacOS X
Classifier: Operating System :: Microsoft :: Windows
License-File: LICENSE
